{
  "job_id": "27c77b13-337f-4904-a993-1289c50dfa0a",
  "scenario": "cir",
  "status": "completed",
  "region": "americas",
  "entity_name": "GALATA CHEMICALS (CANADA) INC.",
  "country": "CA",
  "created_at": "2026-05-22T19:26:27.904885+00:00",
  "updated_at": "2026-05-22T19:33:55.552213+00:00",
  "blob_path": "osint-staging/cir/americas/galata_chemicals_canada_inc_CA_20260522.json",
  "report_summary": "Done.\n\n---\n\n**DONE: Galata Chemicals (Canada) Inc., CA \u2014 Risk: 2 CLEAR \u2014 Ontario #9584188; 10 Reagens Industrial Pkwy, Bradford ON; leading global PVC additives producer (organotin stabilizers, plasticizers, polymer modifiers); SK Capital Partners PE; Argus/WITCO/Chemtura lineage (1960-2010); Ontario Environmental Compliance Approval; all sanctions CLEAR; HudsonRock minor**\n\n---\n\n## \ud83d\udccb CIR: GALATA CHEMICALS (CANADA) INC.\n`galata_chemicals_canada_inc_CA_20260522.json` \u2192 `osint-staging/americas/`\n\n---\n\n### \ud83c\udfe2 Workstream 1A \u2014 Canadian Registry\n\n| Field | Value |\n|---|---|\n| **Ontario Corp #** | **9584188** |\n| Address | **10 Reagens Industrial Pkwy, Bradford, ON L3Z 0Z8** |\n| Phone | 905-775-5000 |\n| Environmental | \u2705 Ontario ERO Compliance Approval (air) \u2014 active manufacturing |\n| Parent | Galata Chemicals LLC \u2014 Jersey City, NJ, USA |\n| PE owner | **SK Capital Partners** (NY) |\n\n---\n\n### \ud83c\udfed Business \u2014 PVC Additives Manufacturer\n\n**\"The Additives Supplier of Choice for over 50 years\"**\n\n| Products | Relevance to Research Queue |\n|---|---|\n| Organotin heat stabilizers | \u2190 **Core input for all PVC pipe manufacturers** |\n| Mixed metal stabilizers (Ca-Zn) | \u2190 PTM Mexico, Plasticos Rival, Plassim, Palad, ALRTIL... |\n| Plasticizers (Drapex Alpha\u00ae) | \u2190 PVC compounding |\n| Polymer modifiers | \u2190 PVC profile/pipe processing |\n\n**Corporate lineage (1960\u21922010\u2192present):** Argus \u2192 WITCO \u2192 Crompton \u2192 Chemtura \u2192 **Galata Chemicals (May 1, 2010 spin-out)**\n\n**Global facilities:** Taft LA \u00b7 Lampertheim DE \u00b7 Dahej IN \u00b7 **Izmir TR (2019)** \u00b7 Bradford CA\n\n---\n\n### \ud83d\udea8 Sanctions: ALL CLEAR | \ud83d\udcbb Dark Web: HudsonRock minor; 0 breaches\n\n### \ud83d\udccc Open Items (all LOW): Ontario registry extract \u00b7 Infostealer notification \u00b7 ECCN verification if re-exporting\n\n**Recommendation: PROCEED WITH STANDARD ONBOARDING.** Major established PVC chemicals supplier \u2014 directly relevant to PVC manufacturing value chain of this research batch.\n---\n\n## DARK WEB SCREENING \u2014 HIGH\n**5 actionable findings** from 5/49 sources via Tor (Netherlands exit node) (11 informational excluded)\n\n| Category | Count |\n|----------|-------|\n| Credential compromise | 1 |\n| Adverse media | 3 |\n| Web mentions (Tor-routed) | 9 |\n| Social media mentions | 1 |\n| Website scans (URLScan) | 1 |\n\n**Key findings:**\n- CREDENTIAL COMPROMISE: www.galatachemicals.com\n- ADVERSE MEDIA: SK Capital Partners Portfolio Investments, SK Capital Partners Funds ... (SK Capital Partners)\n- ADVERSE MEDIA: SK Capital Announces Agreement to Acquire North America Composites ... (SK Capital Partners)\n- ADVERSE MEDIA: SK Capital Closes Fund VI; Exceeds Target at $2.95 Billion (SK Capital Partners)\n\n### Sources with findings\n\n| Source | Findings | Details |\n|--------|----------|---------|\n| duckduckgo_tor | 10 | Galata Chemicals (Canada) Inc; Galata Chemicals (Canada) Inc. | Canada Corporation Director; Company Profile - Galata Chemicals Canada Inc (+7 more) |\n| urlscan | 3 | www.galatachemicals.com; Chemical Manufacturing - Chemical Supplier | Galata Chemical (+1 more) |\n| duckduckgo_adverse | 3 | SK Capital Partners Portfolio Investments, SK Capital Partne; SK Capital Announces Agreement to Acquire North America Comp; SK Capital Closes Fund VI; Exceeds Target at $2.95 Billion |\n| hudsonrock_cavalier | 1 | www.galatachemicals.com |\n| reddit | 1 | Epoxidized Soybean Oil Market 2017: Review, Research, Statis |\n\n### All findings detail\n\n**CREDENTIAL COMPROMISE** (1)\n- www.galatachemicals.com \u2014 *hudsonrock_cavalier*\n\n**ADVERSE MEDIA** (3)\n- SK Capital Partners Portfolio Investments, SK Capital Partners Funds ... \u2014 *duckduckgo_adverse* (searched: SK Capital Partners) [/l/?uddg=https%3A%2F%2Fwww.cbinsights.com%2Finvestor%2Fsk%2Dcapital%2Dpartners&r]\n- SK Capital Announces Agreement to Acquire North America Composites ... \u2014 *duckduckgo_adverse* (searched: SK Capital Partners) [/l/?uddg=https%3A%2F%2Fwww.marketscreener.com%2Fquote%2Fstock%2FPARKER%2DHANNIFI]\n- SK Capital Closes Fund VI; Exceeds Target at $2.95 Billion \u2014 *duckduckgo_adverse* (searched: SK Capital Partners) [/l/?uddg=https%3A%2F%2Fwww.businesswire.com%2Fnews%2Fhome%2F20240404851562%2Fen%]\n\n**WEB MENTION** (9)\n- Galata Chemicals (Canada) Inc \u2014 *duckduckgo_tor* [/l/?uddg=https%3A%2F%2Fwww.galatachemicals.com%2Flocations%2Fgalata%2Dchemicals%]\n- Galata Chemicals (Canada) Inc. | Canada Corporation Directory \u2014 *duckduckgo_tor* [/l/?uddg=https%3A%2F%2Fwww.canadacompanyregistry.com%2Fcompanies%2Fgalata%2Dchem]\n- Company Profile - Galata Chemicals Canada Inc \u2014 *duckduckgo_tor* [/l/?uddg=https%3A%2F%2Fchemdmart.com%2Fcompany%2Dprofile%2Fgalata%2Dchemicals%2D]\n- Galata Chemicals (Canada) Inc. \u00b7 10 Reagens Industrial Parkway ... \u2014 *duckduckgo_tor* [/l/?uddg=https%3A%2F%2Fopengovca.com%2Fcorporation%2F9584188&rut=26a8f7741f50e42]\n- GALATA CHEMICALS (CANADA) INC. - Bizapedia \u2014 *duckduckgo_tor* [/l/?uddg=https%3A%2F%2Fwww.bizapedia.com%2Fcanada%2Fgalata%2Dchemicals%2Dcanada%]\n- Galata Chemicals (Canada) Inc. - Environmental Compliance Approval (air) \u2014 *duckduckgo_tor* [/l/?uddg=https%3A%2F%2Fero.ontario.ca%2Fnotice%2F026%2D0380&rut=8f1bf17cdf2c3768]\n- Galata Chemicals in Bradford, ON L3Z 0Z8 - 905-775-5000 \u2014 *duckduckgo_tor* [/l/?uddg=https%3A%2F%2Fcanada.chamberofcommerce.com%2Fbusiness%2Ddirectory%2Font]\n- Galata Chemicals (Canada) Inc. - Indeed.com \u2014 *duckduckgo_tor* [/l/?uddg=https%3A%2F%2Fca.indeed.com%2Fcmp%2FGalata%2DChemicals%2D(canada)%2DInc]\n- Galata Chemicals (Canada) Inc. - ca.lei.report \u2014 *duckduckgo_tor* [/l/?uddg=https%3A%2F%2Fca.lei.report%2FLEI%2F549300ESOXZTP3HPTM07&rut=ebba4097ef]\n\n**SOCIAL MENTION** (1)\n- Epoxidized Soybean Oil Market 2017: Review, Research, Statistics And Growth To 2025 \u2014 *reddit* [https://reddit.com/r/u_pmrfood/comments/gsnfa0/epoxidized_soybean_oil_market_201]\n\n**DOMAIN SCAN SUMMARY** (1)\n- www.galatachemicals.com \u2014 *urlscan*\n\n**WEBSITE SCAN** (1)\n- Chemical Manufacturing - Chemical Supplier | Galata Chemicals \u2014 *urlscan* [https://www.galatachemicals.com/]\n\n*Full dark web data in blob: `dark_web_screening` + `dark_web_intelligence`*\n\n---",
  "error": null,
  "retry_count": 0,
  "review": null,
  "seed_data": {
    "entity_legal_name": "GALATA CHEMICALS (CANADA) INC.",
    "entity_country": "CA",
    "key_individuals": [],
    "known_affiliates": [],
    "known_suppliers": [],
    "copap_relationship": "Unknown",
    "priority": "standard"
  },
  "region_status": {
    "americas": {
      "status": "completed",
      "error": null
    }
  },
  "dark_web_findings": 5,
  "dark_web_sources": 49
}