{
  "job_id": "dd6ad081-8e8c-4cb5-8a9b-74656f123073",
  "scenario": "cir",
  "status": "completed",
  "region": "gulf",
  "entity_name": "RAR RESIN & CHEMICAL INDUSTRIES DMCC",
  "country": "AE",
  "created_at": "2026-05-22T18:34:11.882888+00:00",
  "updated_at": "2026-05-22T18:46:02.842757+00:00",
  "blob_path": "osint-staging/cir/gulf/rar_resin_chemical_industries_dmcc_AE_20260522.json",
  "report_summary": "Both blobs uploaded (HTTP 201). Both reports complete.\n\n---\n\n## DONE \u2014 Two Reports\n\n---\n\n### 1. ATS SYNTHETIC (Pvt) Ltd., PK \u2014 Risk: **4 REVIEW** \u26a0\ufe0f\n\n**Primary driver: FBR enforcement + tax non-compliance**\n\n| Check | Result |\n|---|---|\n| SECP | \u274c UNVERIFIED via portal (3 name variants tried) |\n| NTN 786227 | \u26a0\ufe0f **VERIFIED_INACTIVE** \u2014 NOT in FBR Active Taxpayer List |\n| FBR Enforcement | \ud83d\udea8 **Rs. 840M (~USD 3M) forcibly recovered; bank accounts frozen (2024)** |\n| Anjum Nisar | \u26a0\ufe0f Former FPCCI President \u2014 PEP-equivalent; EDD required |\n| Moses Platt / Anthony Thunstro | \u2753 Foreign directors; zero web presence \u2014 KYC gap |\n| Baker McKenzie | Legal representation only \u2014 not adverse |\n| NAB | \u2705 No cases |\n| Sanctions | \u2705 No match (OFAC/UN/EU/UK) |\n| Dark Web | \u2705 0 adverse findings |\n| Group | ATS + Nimir Chemical + Nisar Spinning (PACRA A-/A2 Stable) |\n| Products | \u2705 Low-risk PVC/synthetic leather materials |\n\n**Must resolve before transacting**: SECP certificate, FBR ATL explanation + Rs. 840M enforcement resolution, EDD on Anjum Nisar, KYC on foreign directors.\n\n---\n\n### 2. RAR RESIN & CHEMICAL INDUSTRIES DMCC, AE \u2014 Risk: **3 MONITOR**\n\n**Group is genuine; opaque director is the primary concern**\n\n| Check | Result |\n|---|---|\n| DMCC registration | \u2705 2018, regulated free zone |\n| Owner | \u2705 Rabih A Raidi (Lebanese Christian, Jbeil area) \u2014 RAR = initials |\n| Bayer AG license | \u2705 Major legitimacy signal |\n| Samer Elias (DGM/CEO) | \u2705 No adverse findings |\n| Sayyed Sajjad Shahab | \u2753 **Zero web presence \u2014 opaque DMCC director \u2014 high-priority KYC** |\n| Lebanon parent | \u26a0\ufe0f Lebanon added to FATF grey list Oct 2024 |\n| Products | \u26a0\ufe0f NC Solution (nitrocellulose) + Isocyanates \u2014 dual-use; end-use required |\n| Iraq operations | \u26a0\ufe0f Elevated jurisdiction risk |\n| Iran nexus | \u2705 No evidence \u2014 owner is Lebanese Christian, not Iran-linked |\n| Sanctions | \u2705 No match (OFAC/UN/EU/UK) |\n| Dark Web | \u2705 0 adverse findings |\n| Adverse media | \u2705 None found |\n\n**Must resolve before transacting**: Full KYC on Sayyed Sajjad Shahab, UBO declaration, end-use certificate for NC/isocyanate products, UAE bank reference.\n---\n\n## DARK WEB SCREENING \u2014 CRITICAL\n**4 actionable findings** from 5/45 sources via Tor (Netherlands exit node) (12 informational excluded)\n\n| Category | Count |\n|----------|-------|\n| World Bank Debarment | 1 |\n| Credential compromise | 1 |\n| SSL certificates (crt.sh) | 1 |\n| Web mentions (Tor-routed) | 10 |\n| Website scans (URLScan) | 1 |\n\n**Key findings:**\n- WORLD BANK DEBARMENT: \n- CREDENTIAL COMPROMISE: rarresin.com\n\n### Sources with findings\n\n| Source | Findings | Details |\n|--------|----------|---------|\n| duckduckgo_tor | 10 | RAR RESIN & CHEMICAL INDUSTRIES DMCC Company Profile | Dubai; RAR Resin & Chemical Industries DMCC - 2GIS; Rar Resin & Chemicals Industries - Dubai local (+7 more) |\n| crtsh | 4 | rarresin.com; certificate_transparency (+2 more) |\n| urlscan | 2 | rarresin.com; rarresin.com |\n| hudsonrock_cavalier | 1 | rarresin.com |\n| adb_sanctions | 1 | debarment_record |\n\n### All findings detail\n\n**WORLD BANK DEBARMENT** (1)\n-  \u2014 *adb_sanctions* [https://www.adb.org/who-we-are/integrity/sanctions]\n\n**CREDENTIAL COMPROMISE** (1)\n- rarresin.com \u2014 *hudsonrock_cavalier*\n\n**WEB MENTION** (10)\n- RAR RESIN & CHEMICAL INDUSTRIES DMCC Company Profile | Dubai, Dubai ... \u2014 *duckduckgo_tor* [/l/?uddg=https%3A%2F%2Fwww.dnb.com%2Fbusiness%2Ddirectory%2Fcompany%2Dprofiles.r]\n- RAR Resin & Chemical Industries DMCC - 2GIS \u2014 *duckduckgo_tor* [/l/?uddg=https%3A%2F%2F2gis.ae%2Fdubai%2Fbranches%2F70000001006647242&rut=ee7865]\n- Rar Resin & Chemicals Industries - Dubai local \u2014 *duckduckgo_tor* [/l/?uddg=https%3A%2F%2Fdubailocal.ae%2Fbusiness%2Frar%2Dresin%2Dchemicals%2Dindu]\n- Company Profile - Rar Resin And Chemical Industries Dmcc \u2014 *duckduckgo_tor* [/l/?uddg=https%3A%2F%2Fchemdmart.com%2Fcompany%2Dprofile%2Frar%2Dresin%2Dand%2Dc]\n- RAR Resin and Chemical Industries - LinkedIn \u2014 *duckduckgo_tor* [/l/?uddg=https%3A%2F%2Fwww.linkedin.com%2Fcompany%2Frar%2Dresin&rut=cf0cd8f04121]\n- Rar Resin & Chemical Industries (Chemical & Metal Companies ... - HiDubai \u2014 *duckduckgo_tor* [/l/?uddg=https%3A%2F%2Fwww.hidubai.com%2Fbusinesses%2Frar%2Dresin%2Dchemical%2Di]\n- Company Overview - RAR RESIN & CHEMICAL INDUSTRIES DMCC \u2014 *duckduckgo_tor* [/l/?uddg=https%3A%2F%2Frarchemicals.trustpass.alibaba.com%2F&rut=b25d9c8f0ba526d]\n- RAR Resin & Chemical Industries DMCC - maps.urbi.ae \u2014 *duckduckgo_tor* [/l/?uddg=https%3A%2F%2Fmaps.urbi.ae%2Fdubai%2Ffirm%2F70000001060686038&rut=83f77]\n- RAR Holding \u2014 *duckduckgo_tor* [/l/?uddg=https%3A%2F%2Frarholding.com%2F&rut=3d73a13509333ea41d8e2f68292d09be7f6]\n- RAR RESIN & CHEMICAL INDUSTRIES DMCC ,United Arab Emirates \u2014 *duckduckgo_tor* [/l/?uddg=https%3A%2F%2Fwww.company%2Dlisting.org%2Frar_resin_chemical_industries]\n\n**CERTIFICATE SUMMARY** (1)\n- rarresin.com \u2014 *crtsh*\n\n**SSL CERTIFICATE** (1)\n-  \u2014 *crtsh*\n\n**DOMAIN SCAN SUMMARY** (1)\n- rarresin.com \u2014 *urlscan*\n\n**WEBSITE SCAN** (1)\n- rarresin.com \u2014 *urlscan* [http://rarresin.com/]\n\n*Full dark web data in blob: `dark_web_screening` + `dark_web_intelligence`*\n\n---",
  "error": null,
  "retry_count": 0,
  "review": null,
  "seed_data": {
    "entity_legal_name": "RAR RESIN & CHEMICAL INDUSTRIES DMCC",
    "entity_trade_names": "RAR Resin & Chemical Industries DMCC",
    "entity_country": "AE",
    "entity_address": "Unit 1107, 11th Floor, 1 Lake Plaza, Plot JLT-PH2-T2A, Jumeirah Lakes Towers, Dubai, UAE",
    "entity_website": "https://rarresin.com",
    "entity_type": "Trading",
    "entity_industry": "Trading",
    "key_individuals": [
      {
        "name": "Sayyed Sajjad Shahab"
      },
      {
        "name": "Samer Elias"
      }
    ],
    "known_affiliates": [],
    "known_suppliers": [],
    "copap_relationship": "Unknown",
    "copap_products": "Xylene (1500 MT monthly consumption equivalent)",
    "priority": "standard"
  },
  "region_status": {
    "gulf": {
      "status": "completed",
      "error": null
    }
  },
  "dark_web_findings": 4,
  "dark_web_sources": 45
}